pentagon/__init__.py
pentagon/cli.py
pentagon/defaults.py
pentagon/filters.py
pentagon/helpers.py
pentagon/meta.py
pentagon/pentagon.py
pentagon/component/__init__.py
pentagon/component/aws_vpc/__init__.py
pentagon/component/aws_vpc/files/aws_vpc.auto.tfvars.jinja
pentagon/component/aws_vpc/files/aws_vpc.tf.jinja
pentagon/component/aws_vpc/files/aws_vpc_variables.tf
pentagon/component/core/__init__.py
pentagon/component/core/files/.gitignore
pentagon/component/core/files/README.md
pentagon/component/core/files/ansible-requirements.yml
pentagon/component/core/files/requirements.txt
pentagon/component/core/files/inventory/__init__.py
pentagon/component/core/files/plugins/filter_plugins/flatten.py
pentagon/component/core/files/plugins/inventory/base
pentagon/component/core/files/plugins/inventory/ec2.ini
pentagon/component/core/files/plugins/inventory/ec2.py
pentagon/component/gcp/__init__.py
pentagon/component/gcp/cluster.py
pentagon/component/gcp/files/public_cluster/cluster.tf.jinja
pentagon/component/inventory/__init__.py
pentagon/component/inventory/files/__init__.py
pentagon/component/inventory/files/common/clusters/__init__.py
pentagon/component/inventory/files/common/config/local/ansible.cfg-default.jinja
pentagon/component/inventory/files/common/config/local/local-config-init.jinja
pentagon/component/inventory/files/common/config/local/ssh_config-default.jinja
pentagon/component/inventory/files/common/config/local/vars.yml.jinja
pentagon/component/inventory/files/common/config/private/.gitignore
pentagon/component/inventory/files/common/config/private/secrets.yml.jinja
pentagon/component/inventory/files/common/kubernetes/__init__.py
pentagon/component/inventory/files/common/terraform/.gitignore
pentagon/component/inventory/files/common/terraform/backend.tf.jinja
pentagon/component/inventory/files/common/terraform/provider.tf.jinja
pentagon/component/kops/__init__.py
pentagon/component/kops/files/cluster.yml.jinja
pentagon/component/kops/files/kops.sh
pentagon-3.1.4.dist-info/LICENSE
pentagon-3.1.4.dist-info/METADATA
pentagon-3.1.4.dist-info/WHEEL
pentagon-3.1.4.dist-info/entry_points.txt
pentagon-3.1.4.dist-info/top_level.txt
pentagon-3.1.4.dist-info/RECORD
