Metadata-Version: 2.1
Name: pentagon
Version: 3.1.4
Summary: Radically simple kubernetes
Home-page: http://reactiveops.com/
Author: ReactiveOps, Inc.
Author-email: services@reactiveops.com
License: Apache2.0
Platform: UNKNOWN
Classifier: Development Status :: 5 - Production/Stable
Classifier: Environment :: Console
Classifier: Intended Audience :: Developers
Classifier: Intended Audience :: Information Technology
Classifier: Intended Audience :: System Administrators
Classifier: License :: OSI Approved :: Apache Software License
Classifier: Natural Language :: English
Classifier: Operating System :: POSIX
Classifier: Programming Language :: Python :: 2.6
Classifier: Programming Language :: Python :: 2.7
Classifier: Topic :: System :: Installation/Setup
Classifier: Topic :: System :: Systems Administration
Classifier: Topic :: Utilities
Requires-Dist: click (==6.7)
Requires-Dist: GitPython (==2.1.3)
Requires-Dist: Jinja2 (==2.9.5)
Requires-Dist: pycrypto (==2.6.1)
Requires-Dist: oyaml (>=0.8)
Requires-Dist: PyYAML (>=5.0)
Requires-Dist: shyaml (==0.6.1)
Requires-Dist: ansible (==2.5.2)
Requires-Dist: awscli (>=1.16.0)
Requires-Dist: boto3 (>=1.9.0)
Requires-Dist: botocore (>=1.12.0)
Requires-Dist: boto (==2.49.0)
Requires-Dist: google-api-python-client (==1.6.2)
Requires-Dist: coloredlogs (==9.0)
Requires-Dist: semver (>=2.8.0)
